README.md
setup.py
haste_storage_client/__init__.py
haste_storage_client/core.py
haste_storage_client.egg-info/PKG-INFO
haste_storage_client.egg-info/SOURCES.txt
haste_storage_client.egg-info/dependency_links.txt
haste_storage_client.egg-info/requires.txt
haste_storage_client.egg-info/top_level.txt
haste_storage_client/models/__init__.py
haste_storage_client/models/interestingness_model.py
haste_storage_client/models/random_interestingness_model.py
haste_storage_client/models/rest_interestingness_model.py
haste_storage_client/storage/__init__.py
haste_storage_client/storage/pachyderm.py
haste_storage_client/storage/storage.py