Metadata-Version: 1.0
Name: haste-storage-client
Version: 0.13
Summary: Client for the HASTE storage plaform: http://haste.research.it.uu.se
Home-page: http://haste.research.it.uu.se
Author: Ben Blamey
Author-email: ben.blamey@it.uu.se
License: UNKNOWN
Platform: UNKNOWN
